Workbook

Sheet Main
B3: USD (in thousands) | I3: Price | J3: 2.9
I4: Shares | J4: 158948.69
I5: MC | J5: =J3*J4 -> 460951.2
I6: Cash | J6: 307883
I7: Debt | J7: 600076
I8: EV | J8: =J5+J7-J6 -> 753144.2
J9: =J8/'Income Statement(a)'!F10 -> 3.9272487

Sheet Income Statement(a)
C2: 2021 | D2: 2022 | E2: 2023 | F2: 2024 | G2: =F2+1 -> 2025 | H2: =G2+1 -> 2026 | I2: =H2+1 -> 2027 | J2: =I2+1 -> 2028 | K2: =J2+1 -> 2029 | L2: =K2+1 -> 2030 | M2: =L2+1 -> 2031 | N2: =M2+1 -> 2032 | ... Q2: =P2+1 -> 2035
B3: Revenue | C3: 760910 | D3: 903503 | E3: 1051830 | F3: 1071643 | G3: =SUM('Income Statement(q)'!E3:H3) -> 987656 | H3: =G3*0.97 -> 958026.32 | I3: =H3*0.97 -> 929285.53 | J3: =I3*0.97 -> 901406.96 | K3: =J3*0.97 -> 874364.76 | L3: =K3*0.97 -> 848133.81 | M3: =L3*0.97 -> 822689.8 | N3: =M3*0.97 -> 798009.1 | O3: =N3*0.97 -> 774068.83 | ... Q3: =P3*0.97 -> 728321.36
B4: COGS | C4: -205573 | D4: -249490 | E4: -307835 | F4: -318835 | G4: =SUM('Income Statement(q)'!E4:H4) -> -288297.27 | H4: -318835 | I4: -318835 | J4: -318835 | K4: -318835 | L4: -318835 | M4: -318835 | N4: -318835 | O4: -318835 | P4: -318835 | Q4: -318835
B5: Gross Profit | C5: =C3+C4 -> 555337 | D5: =D3+D4 -> 654013 | E5: =E3+E4 -> 743995 | F5: =F3+F4 -> 752808 | G5: =SUM('Income Statement(q)'!E5:H5) -> 699358.73 | H5: =H3*(G5/G3+0.0005) -> 678856.98 | I5: =I3*(H5/H3+0.0005) -> 658955.91 | J5: =J3*(I5/I3+0.0005) -> 639637.94 | K5: =K3*(J5/J3+0.0005) -> 620885.98 | L5: =L3*(K5/K3+0.0005) -> 602683.47 | M5: =M3*(L5/L3+0.0005) -> 585014.31 | N5: =N3*(M5/M3+0.0005) -> 567862.89 | O5: =O3*(N5/N3+0.0005) -> 551214.04 | ... Q5: =Q3*(P5/P3+0.0005) -> 519365.61
B6: SG&A | C6: -469200 | D6: -412736 | E6: -492029 | F6: -389693 | G6: =SUM('Income Statement(q)'!E6:H6) -> -307418.16 | H6: =H3*(G6/G3+0.0001) -> -298099.81 | I6: =I3*(H6/H3+0.0001) -> -289063.89 | J6: =J3*(I6/I3+0.0001) -> -280301.83 | K6: =K3*(J6/J3+0.0001) -> -271805.34 | L6: =L3*(K6/K3+0.0001) -> -263566.37 | M6: =M3*(L6/L3+0.0001) -> -255577.11 | N6: =N3*(M6/M3+0.0001) -> -247829.99 | O6: =O3*(N6/N3+0.0001) -> -240317.69 | ... Q6: =Q3*(P6/P3+0.0001) -> -225969.25
B7: R&D | C7: -113764 | D7: -109020 | E7: -130565 | F7: -100725 | G7: =SUM('Income Statement(q)'!E7:H7) -> -126167.56 | H7: =H3*(G7/G3+0.0005) -> -121903.52 | I7: =I3*(H7/H3+0.0005) -> -117781.77 | J7: =J3*(I7/I3+0.0005) -> -113797.62 | K7: =K3*(J7/J3+0.0005) -> -109946.5 | L7: =L3*(K7/K3+0.0005) -> -106224.04 | M7: =M3*(L7/L3+0.0005) -> -102625.98 | N7: =N3*(M7/M3+0.0005) -> -99148.192 | O7: =O3*(N7/N3+0.0005) -> -95786.712 | ... Q7: =Q3*(P7/P3+0.0005) -> -89397.396
B8: Others | C8: -107056 | D8: -89713 | E8: -68028 | F8: -70616 | G8: =SUM('Income Statement(q)'!E8:H8) -> -28242.89 | H8: =H3*(G8/G3+0.0005) -> -26916.59 | I8: =I3*(H8/H3+0.0005) -> -25644.45 | J8: =J3*(I8/I3+0.0005) -> -24424.413 | K8: =K3*(J8/J3+0.0005) -> -23254.498 | L8: =L3*(K8/K3+0.0005) -> -22132.796 | M8: =M3*(L8/L3+0.0005) -> -21057.467 | N8: =N3*(M8/M3+0.0005) -> -20026.739 | O8: =O3*(N8/N3+0.0005) -> -19038.902 | ... Q8: =Q3*(P8/P3+0.0005) -> -17185.382
B9: Operating Expense | C9: =C6+C7+C8 -> -690020 | D9: =D6+D7+D8 -> -611469 | E9: =E6+E7+E8 -> -690622 | F9: =F6+F7+F8 -> -561034 | G9: =SUM('Income Statement(q)'!E9:H9) -> -461828.61 | H9: =H6+H7+H8 -> -446919.92 | I9: =I6+I7+I8 -> -432490.11 | J9: =J6+J7+J8 -> -418523.86 | K9: =K6+K7+K8 -> -405006.34 | L9: =L6+L7+L8 -> -391923.21 | M9: =M6+M7+M8 -> -379260.55 | N9: =N6+N7+N8 -> -367004.92 | O9: =O6+O7+O8 -> -355143.3 | ... Q9: =Q6+Q7+Q8 -> -332552.02
B10: Operating Income | C10: =C5+C9 -> -134683 | D10: =D5+D9 -> 42544 | E10: =E5+E9 -> 53373 | F10: =F5+F9 -> 191774 | G10: =SUM('Income Statement(q)'!E10:H10) -> 237530.12 | H10: =H5+H9 -> 231937.06 | I10: =I5+I9 -> 226465.8 | J10: =J5+J9 -> 221114.08 | K10: =K5+K9 -> 215879.64 | L10: =L5+L9 -> 210760.27 | M10: =M5+M9 -> 205753.76 | N10: =N5+N9 -> 200857.96 | O10: =O5+O9 -> 196070.74 | ... Q10: =Q5+Q9 -> 186813.58
B11: Net Interest | C11: -24574 | D11: -24063 | E11: -21534 | F11: -39945 | G11: =SUM('Income Statement(q)'!E11:H11) -> -32949
B12: Other Income | C12: 3160 | D12: -129199 | E12: -26537 | F12: -897075 | G12: =SUM('Income Statement(q)'!E12:H12) -> -419032
B13: Pretax Income | C13: =C10+C11+C12 -> -156097 | D13: =D10+D11+D12 -> -110718 | E13: =E10+E11+E12 -> 5302 | F13: =F10+F11+F12 -> -745246 | G13: =SUM('Income Statement(q)'!E13:H13) -> -214450.88 | H13: =H10+H11+H12 -> 231937.06 | I13: =I10+I11+I12 -> 226465.8 | J13: =J10+J11+J12 -> 221114.08 | K13: =K10+K11+K12 -> 215879.64 | L13: =L10+L11+L12 -> 210760.27 | M13: =M10+M11+M12 -> 205753.76 | N13: =N10+N11+N12 -> 200857.96 | O13: =O10+O11+O12 -> 196070.74 | ... Q13: =Q10+Q11+Q12 -> 186813.58
B14: Taxes | C14: 437837 | D14: -3406 | E14: -7170 | F14: -23128 | G14: =SUM('Income Statement(q)'!E14:H14) -> -33792.824 | H14: =H13*-0.2 -> -46387.412 | I14: =I13*-0.2 -> -45293.161 | J14: =J13*-0.2 -> -44222.816 | K14: =K13*-0.2 -> -43175.928 | L14: =L13*-0.2 -> -42152.053 | M14: =M13*-0.2 -> -41150.752 | N14: =N13*-0.2 -> -40171.593 | O14: =O13*-0.2 -> -39214.147 | ... Q14: =Q13*-0.2 -> -37362.717
B15: After-Tax Adj | C15: 28075 | D15: 34378 | E15: -2345 | F15: 211366 | G15: =SUM('Income Statement(q)'!E15:H15) -> 92545
B16: Net Income | C16: =C13+C14+C15 -> 309815 | D16: =D13+D14+D15 -> -79746 | E16: =E13+E14+E15 -> -4213 | F16: =F13+F14+F15 -> -557008 | G16: =SUM('Income Statement(q)'!E16:H16) -> -155698.7 | H16: =H13+H14+H15 -> 185549.65 | I16: =I13+I14+I15 -> 181172.64 | J16: =J13+J14+J15 -> 176891.26 | K16: =K13+K14+K15 -> 172703.71 | L16: =L13+L14+L15 -> 168608.21 | M16: =M13+M14+M15 -> 164603.01 | N16: =N13+N14+N15 -> 160686.37 | O16: =O13+O14+O15 -> 156856.59 | ... Q16: =Q13+Q14+Q15 -> 149450.87
B17: Other Stockholders | C17: -128176 | D17: 55 | E17: -73 | F17: -259 | G17: =SUM('Income Statement(q)'!E17:H17) -> -4
B18: NI Common | C18: =C16+C17 -> 181639 | D18: =D16+D17 -> -79691 | E18: =E16+E17 -> -4286 | F18: =F16+F17 -> -557267 | G18: =SUM('Income Statement(q)'!E18:H18) -> -155702.7 | H18: =H16+H17 -> 185549.65 | I18: =I16+I17 -> 181172.64 | J18: =J16+J17 -> 176891.26 | K18: =K16+K17 -> 172703.71 | L18: =L16+L17 -> 168608.21 | M18: =M16+M17 -> 164603.01 | N18: =N16+N17 -> 160686.37 | O18: =O16+O17 -> 156856.59 | ... Q18: =Q16+Q17 -> 149450.87 | R18: =Q18*(1+$T$22) -> 149450.87 | S18: =R18*(1+$T$22) -> 149450.87 | T18: =S18*(1+$T$22) -> 149450.87 | U18: =T18*(1+$T$22) -> 149450.87 | V18: =U18*(1+$T$22) -> 149450.87 | W18: =V18*(1+$T$22) -> 149450.87 | X18: =W18*(1+$T$22) -> 149450.87 | Y18: =X18*(1+$T$22) -> 149450.87 | ... FW18: =FV18*(1+$T$22) -> 149450.87
B19: Avg Shares | C19: 129213 | D19: 129774 | E19: 140433 | F19: 120825 | G19: ='Income Statement(q)'!H19 -> 113145
B22: Rev Growth | C22: 0 | D22: =IFERROR((D3-C3)/C3,0) -> 0.18739798 | E22: =IFERROR((E3-D3)/D3,0) -> 0.1641688 | F22: =IFERROR((F3-E3)/E3,0) -> 0.018836694 | G22: =IFERROR((G3-F3)/F3,0) -> -0.078372182 | H22: =IFERROR((H3-G3)/G3,0) -> -0.03 | I22: =IFERROR((I3-H3)/H3,0) -> -0.03 | J22: =IFERROR((J3-I3)/I3,0) -> -0.03 | K22: =IFERROR((K3-J3)/J3,0) -> -0.03 | ... Q22: =IFERROR((Q3-P3)/P3,0) -> -0.03 | S22: Mautrity | T22: 0
B23: Gross Margin | C23: =C5/C3 -> 0.7298327 | D23: =D5/D3 -> 0.72386367 | E23: =E5/E3 -> 0.70733388 | F23: =F5/F3 -> 0.70248021 | G23: =G5/G3 -> 0.70809951 | H23: =H5/H3 -> 0.70859951 | I23: =I5/I3 -> 0.70909951 | J23: =J5/J3 -> 0.70959951 | ... Q23: =Q5/Q3 -> 0.71309951 | S23: Discount | T23: 0.1
B24: Op Margin | C24: =C10/C3 -> -0.17700254 | D24: =D10/D3 -> 0.047087835 | E24: =E10/E3 -> 0.050742991 | F24: =F10/F3 -> 0.17895325 | G24: =G10/G3 -> 0.24049884 | H24: =H10/H3 -> 0.24209884 | I24: =I10/I3 -> 0.24369884 | J24: =J10/J3 -> 0.24529884 | ... Q24: =Q10/Q3 -> 0.25649884 | S24: NPV | T24: =NPV(T23,H18:FW18)+Main!J6-Main!J7 -> 1329068.6
B25: Net Margin | C25: =C18/C3 -> 0.23871286 | D25: =D18/D3 -> -0.088202253 | E25: =E18/E3 -> -0.004074803 | F25: =F18/F3 -> -0.52001179 | G25: =G18/G3 -> -0.15764872 | H25: =H18/H3 -> 0.19367907 | I25: =I18/I3 -> 0.19495907 | J25: =J18/J3 -> 0.19623907 | ... Q25: =Q18/Q3 -> 0.20519907 | S25: Price | T25: =T24/Main!J4 -> 8.3616206
S26: Difference | T26: =T25/Main!J3-1 -> 1.8833174

Sheet Income Statement(q)
C2: FY24Q3 | D2: FY24Q4 | E2: FY25Q1 | F2: FY25Q2 | G2: FY25Q3 | H2: FY25Q4
B3: Revenue | C3: 273605 | D3: 261648 | E3: 247101 | F3: 248229 | G3: 246163 | H3: =G3 -> 246163
B4: COGS | C4: -79552 | D4: -77953 | E4: -73353 | F4: -74338 | G4: -69219 | H4: =H5-H3 -> -71387.27
B5: Gross Profit | C5: =C3+C4 -> 194053 | D5: =D3+D4 -> 183695 | E5: =E3+E4 -> 173748 | F5: =F3+F4 -> 173891 | G5: =G3+G4 -> 176944 | H5: =H3*0.71 -> 174775.73
B6: SG&A | C6: -96800 | D6: -104529 | E6: -81378 | F6: -68238 | G6: -79030 | H6: =H3*-0.32 -> -78772.16
B7: R&D | C7: -24880 | D7: -24123 | E7: -34504 | F7: -32510 | G7: -29614 | H7: =H3*-0.12 -> -29539.56
B8: Others | C8: -18312 | D8: -18074 | E8: -9585 | F8: -6631 | G8: -4642 | H8: =H3*-0.03 -> -7384.89
B9: Operating Expense | C9: =C6+C7+C8 -> -139992 | D9: =D6+D7+D8 -> -146726 | E9: =E6+E7+E8 -> -125467 | F9: =F6+F7+F8 -> -107379 | G9: =G6+G7+G8 -> -113286 | H9: =H6+H7+H8 -> -115696.61
B10: Operating Income | C10: =C5+C9 -> 54061 | D10: =D5+D9 -> 36969 | E10: =E5+E9 -> 48281 | F10: =F5+F9 -> 66512 | G10: =G5+G9 -> 63658 | H10: =H5+H9 -> 59079.12
B11: Net Interest | C11: -9809 | D11: -12136 | E11: -12049 | F11: -10259 | G11: -10641
B12: Other Income | C12: -889350 | D12: -8642 | E12: -10393 | F12: -416767 | G12: 8128
B13: Pretax Income | C13: =C10+C11+C12 -> -845098 | D13: =D10+D11+D12 -> 16191 | E13: =E10+E11+E12 -> 25839 | F13: =F10+F11+F12 -> -360514 | G13: =G10+G11+G12 -> 61145 | H13: =H10+H11+H12 -> 59079.12
B14: Taxes | C14: -4161 | D14: -6865 | E14: -6008 | F14: -6469 | G14: -9500 | H14: =H13*-0.2 -> -11815.824
B15: After-Tax Adj | C15: 236060 | D15: -5147 | E15: -6387 | F15: 113239 | G15: -14307
B16: Net Income | C16: =C13+C14+C15 -> -613199 | D16: =D13+D14+D15 -> 4179 | E16: =E13+E14+E15 -> 13444 | F16: =F13+F14+F15 -> -253744 | G16: =G13+G14+G15 -> 37338 | H16: =H13+H14+H15 -> 47263.296
B17: Other Stockholders | C17: -211 | D17: 5220 | E17: -1 | F17: -4 | G17: 1
B18: NI Common | C18: =C16+C17 -> -613410 | D18: =D16+D17 -> 9399 | E18: =E16+E17 -> 13443 | F18: =F16+F17 -> -253748 | G18: =G16+G17 -> 37339 | H18: =H16+H17 -> 47263.296
B19: Avg Shares | C19: 120000 | D19: 107108 | E19: 103415 | F19: 103952 | G19: 113145 | H19: 113145
B22: Rev Growth | C22: 0 | D22: =IFERROR((D3-C3)/C3,0) -> -0.043701687 | E22: =IFERROR((E3-D3)/D3,0) -> -0.055597597 | F22: =IFERROR((F3-E3)/E3,0) -> 0.004564935 | G22: =IFERROR((G3-F3)/F3,0) -> -0.0083229598 | H22: =IFERROR((H3-G3)/G3,0) -> 0
B23: Gross Margin | C23: =C5/C3 -> 0.70924508 | D23: =D5/D3 -> 0.70206919 | E23: =E5/E3 -> 0.70314568 | F23: =F5/F3 -> 0.70052653 | G23: =G5/G3 -> 0.71880827 | H23: =H5/H3 -> 0.71
B24: Op Margin | C24: =C10/C3 -> 0.19758776 | D24: =D10/D3 -> 0.14129288 | E24: =E10/E3 -> 0.19538974 | F24: =F10/F3 -> 0.26794613 | G24: =G10/G3 -> 0.25860101 | H24: =H10/H3 -> 0.24
B25: Net Margin | C25: =C18/C3 -> -2.2419546 | D25: =D18/D3 -> 0.035922308 | E25: =E18/E3 -> 0.054402856 | F25: =F18/F3 -> -1.0222335 | G25: =G18/G3 -> 0.15168405 | H25: =H18/H3 -> 0.192

Sheet Cash Flow(a)
C2: 2021 | D2: 2022 | E2: 2023 | F2: 2024
B3: Net Income | C3: 309815 | D3: -79746 | E3: -4213 | F3: -557008
B4: D&A | C4: 107056 | D4: 89713 | E4: 68028 | F4: 70616
B5: Change In Working Capital | C5: -56476 | D5: -34928 | E5: 8670 | F5: -87388
B6: Other Adj | C6: -255558 | D6: 157902 | E6: 109601 | F6: 697221
B7: CFO | C7: 104837 | D7: 132941 | E7: 182086 | F7: 123441
B8: Purchase Of Business | C8: 0 | D8: -69720 | E8: -9820 | F8: 0
B9: Purchase Of Investment | C9: 0 | D9: 0 | E9: 0 | F9: 0
B10: Sale Of Investment | C10: 0 | D10: 0 | E10: 0 | F10: 0
B11: Other Investing | C11: -12484 | D11: -16333 | E11: -14935 | F11: -26754
B12: CFI | C12: -12484 | D12: -86053 | E12: -24755 | F12: -26754
B13: Repayment Of Debt | C13: -206438 | D13: -5750 | E13: -5750 | F13: -5750
B14: Repurchase Of Capital Stock | C14: -1991654 | D14: 0 | E14: -157139 | F14: -214297
... B24: Cap Ex | C24: -13653 | D24: -16333 | E24: -14935 | F24: -26754
B25: FCF | C25: =C23 -> 104837 | D25: =D23 -> 132941 | E25: =E23 -> 182086 | F25: =F23 -> 123441
B28: CFGrowth | C28: 0 | D28: 0.2681 | E28: 0.3697 | F28: -0.3221
B29: CXChange | C29: 0 | D29: 0.1963 | E29: -0.0856 | F29: 0.7914
B30: FCFGrowth | C30: 0 | D30: 0.2788 | E30: 0.4334 | F30: -0.4216
B31: FCFMargin | C31: 0.8698 | D31: 0.8771 | E31: 0.918 | F31: 0.7833

Sheet Cash Flow(q)
C2: FY24Q3 | D2: FY24Q4 | E2: FY25Q1 | F2: FY25Q2 | G2: FY25Q3
B3: Net Income | C3: -613199 | D3: 4179 | E3: 13444 | F3: -253744 | G3: 37338
B4: D&A | C4: 18312 | D4: 18074 | E4: 9585 | F4: 6631 | G4: 4642
B5: Change In Working Capital | C5: 21512 | D5: -55678 | E5: -9186 | F5: 1248 | G5: 17476
B6: Other Adj | C6: 666869 | D6: 28027 | E6: 29402 | F6: 317101 | G6: 17363
B7: CFO | C7: 93494 | D7: -5398 | E7: 43245 | F7: 71236 | G7: 76819
B8: Purchase Of Business | C8: 0 | D8: 0 | E8: 0 | F8: 0 | G8: 0
B9: Purchase Of Investment | C9: 0 | D9: 0 | E9: 0 | F9: 0 | G9: 0
B10: Sale Of Investment | C10: 0 | D10: 0 | E10: 0 | F10: 0 | G10: 0
B11: Other Investing | C11: -19054 | D11: -3169 | E11: -2411 | F11: -3509 | G11: -3025
B12: CFI | C12: -19054 | D12: -3169 | E12: -2411 | F12: -3509 | G12: -3025
B13: Repayment Of Debt | C13: -1438 | D13: -1437 | E13: -1438 | F13: -1437 | G13: -26437
B14: Repurchase Of Capital Stock | C14: -89764 | D14: -40270 | E14: -28682 | F14: 0 | G14: 0
... B24: Cap Ex | C24: -19054 | D24: -3169 | E24: -2411 | F24: -3509 | G24: -3025
B25: FCF | C25: =C23 -> 93494 | D25: =D23 -> -5398 | E25: =E23 -> 43245 | F25: =F23 -> 71236 | G25: =G23 -> 76819
B28: CFGrowth | C28: 0 | D28: 0 | E28: 0 | F28: 0.6473 | G28: 0.0784
B29: CXChange | C29: 0 | D29: -0.8337 | E29: -0.2392 | F29: 0.4554 | G29: -0.1379
B30: FCFGrowth | C30: 0 | D30: 0 | E30: 0 | F30: 0.6586 | G30: 0.0896
B31: FCFMargin | C31: 0.7962 | D31: 0 | E31: 0.9442 | F31: 0.9507 | G31: 0.9606

Sheet Balance Sheet(a)
C2: 2021 | D2: 2022 | E2: 2023 | F2: 2024
B3: Cash & Short Inv | C3: 369175 | D3: 402559 | E3: 355642 | F3: 204319
B4: Accounts Receivable | C4: 47538 | D4: 66930 | E4: 102677 | F4: 99687
B5: Inventory | C5: 0 | D5: 0 | E5: 0 | F5: 0
B6: Other Current Assets | C6: 52751 | D6: 31882 | E6: 34732 | F6: 38236
B7: Current Assets | C7: 469464 | D7: 501371 | E7: 493051 | F7: 342242
B8: PPE | C8: 41037 | D8: 31886 | E8: 27887 | F8: 19727
B9: Goodwill | C9: 1540112 | D9: 1579770 | E9: 1585750 | F9: 1386229
B10: Other Assets | C10: 1726383 | D10: 1579594 | E10: 1518439 | F10: 776689
B11: Non-Current Assets | C11: 3307532 | D11: 3191250 | E11: 3132076 | F11: 2182645
B12: Total Assets | C12: =C7+C11 -> 3776996 | D12: =D7+D11 -> 3692621 | E12: =E7+E11 -> 3625127 | F12: =F7+F11 -> 2524887
B13: Accounts Payable | C13: 19169 | D13: 3367 | E13: 4611 | F13: 6609
B14: Short Term Debt | C14: 9648 | D14: 8885 | E14: 6921 | F14: 8849
B15: Other Current Liabilities | C15: 147153 | D15: 199416 | E15: 233377 | F15: 123112
B16: Current Liabilities | C16: 175970 | D16: 211668 | E16: 244909 | F16: 138570
B17: Long Term Debt | C17: 644942 | D17: 632973 | E17: 628449 | F17: 620667
B18: Other Liabilities | C18: 486315 | D18: 394401 | E18: 414496 | F18: 416596
B19: Non-Current Liabilities | C19: 1131257 | D19: 1027374 | E19: 1042945 | F19: 1037263
B20: Total Liabilities | C20: =C16+C19 -> 1307227 | D20: =D16+D19 -> 1239042 | E20: =E16+E19 -> 1287854 | F20: =F16+F19 -> 1175833
B21: Additional Paid In Capital | C21: 1588426 | D21: 1691911 | E21: 1772449 | F21: 1453483
B22: Retained Earnings | C22: -60125 | D22: -139871 | E22: -144084 | F22: -701092
B23: Accumulated Other Changes | C23: 79895 | D23: 75775 | E23: 6650 | F23: 72144
B24: Stockholders Equity | C24: 1608196 | D24: 1627815 | E24: 1635015 | F24: 824535
B25: Non-Controlling Interest | C25: 861573 | D25: 825764 | E25: 702258 | F25: 524519
B26: Total Equity | C26: =C12+C20 -> 5084223 | D26: =D12+D20 -> 4931663 | E26: =E12+E20 -> 4912981 | F26: =F12+F20 -> 3700720
B27: Common Stock Equity | C27: 1608196 | D27: 1627815 | E27: 1635015 | F27: 824535
B28: Total Debt | C28: 654590 | D28: 641858 | E28: 635370 | F28: 629516
B29: Net Debt | C29: 285415 | D29: 239299 | E29: 279728 | F29: 425197
B30: Tangible Assets | C30: 41037 | D30: 31886 | E30: 27887 | F30: 19727
B31: Invested Capital | C31: 2729575 | D31: 2675993 | E31: 2602557 | F31: 1761831
B32: NCAV | C32: -837763 | D32: -737671 | E32: -794803 | F32: -833591
B33: Shares | C33: 129213 | D33: 129774 | E33: 130688 | F33: 107108
B36: D_E | C36: 0.265 | D36: 0.2616 | E36: 0.2718 | F36: 0.4666
B37: Assets Growth | C37: 0 | D37: -0.0223 | E37: -0.0183 | F37: -0.3035
B38: TAGrowth | C38: 0 | D38: -0.223 | E38: -0.1254 | F38: -0.2926
B39: Equity Growth | C39: 0 | D39: 0.0122 | E39: 0.0044 | F39: -0.4957
B40: ICGrowth | C40: 0 | D40: -0.0196 | E40: -0.0274 | F40: -0.323

Sheet Balance Sheet(q)
C2: FY24Q3 | D2: FY24Q4 | E2: FY25Q1 | F2: FY25Q2 | G2: FY25Q3
B3: Cash & Short Inv | C3: 252057 | D3: 204319 | E3: 202243 | F3: 261739 | G3: 307883
B4: Accounts Receivable | C4: 102547 | D4: 99687 | E4: 98059 | F4: 97395 | G4: 92502
B5: Inventory | C5: 0 | D5: 0 | E5: 0 | F5: 0 | G5: 0
B6: Other Current Assets | C6: 28725 | D6: 38236 | E6: 37551 | F6: 38933 | G6: 36961
B7: Current Assets | C7: 383329 | D7: 342242 | E7: 337853 | F7: 398067 | G7: 437346
B8: PPE | C8: 22277 | D8: 19727 | E8: 18761 | F8: 19412 | G8: 17144
B9: Goodwill | C9: 1389002 | D9: 1386229 | E9: 1387713 | F9: 1129007 | G9: 1129007
B10: Other Assets | C10: 794804 | D10: 776689 | E10: 763965 | F10: 615009 | G10: 609355
B11: Non-Current Assets | C11: 2206083 | D11: 2182645 | E11: 2170439 | F11: 1763428 | G11: 1755506
B12: Total Assets | C12: =C7+C11 -> 2589412 | D12: =D7+D11 -> 2524887 | E12: =E7+E11 -> 2508292 | F12: =F7+F11 -> 2161495 | G12: =G7+G11 -> 2192852
B13: Accounts Payable | C13: 6830 | D13: 6609 | E13: 4803 | F13: 8867 | G13: 3708
B14: Short Term Debt | C14: 8302 | D14: 8849 | E14: 8989 | F14: 9173 | G14: 9143
B15: Other Current Liabilities | C15: 167860 | D15: 123112 | E15: 105670 | F15: 102455 | G15: 110331
B16: Current Liabilities | C16: 182992 | D16: 138570 | E16: 119462 | F16: 120495 | G16: 123182
B17: Long Term Debt | C17: 623599 | D17: 620667 | E17: 619146 | F17: 617816 | G17: 590933
B18: Other Liabilities | C18: 415958 | D18: 416596 | E18: 415443 | F18: 418691 | G18: 441697
B19: Non-Current Liabilities | C19: 1039557 | D19: 1037263 | E19: 1034589 | F19: 1036507 | G19: 1032630
B20: Total Liabilities | C20: =C16+C19 -> 1222549 | D20: =D16+D19 -> 1175833 | E20: =E16+E19 -> 1154051 | F20: =F16+F19 -> 1157002 | G20: =G16+G19 -> 1155812
B21: Additional Paid In Capital | C21: 1749314 | D21: 1453483 | E21: 1381083 | F21: 1384634 | G21: 1441020
B22: Retained Earnings | C22: -705271 | D22: -701092 | E22: -687648 | F22: -941392 | G22: -904054
B23: Accumulated Other Changes | C23: -191481 | D23: 72144 | E23: 121079 | F23: 134369 | G23: 138496
B24: Stockholders Equity | C24: 852562 | D24: 824535 | E24: 814514 | F24: 577611 | G24: 675462
B25: Non-Controlling Interest | C25: 514301 | D25: 524519 | E25: 539727 | F25: 426882 | G25: 361578
B26: Total Equity | C26: =C12+C20 -> 3811961 | D26: =D12+D20 -> 3700720 | E26: =E12+E20 -> 3662343 | F26: =F12+F20 -> 3318497 | G26: =G12+G20 -> 3348664
B27: Common Stock Equity | C27: 852562 | D27: 824535 | E27: 814514 | F27: 577611 | G27: 675462
B28: Total Debt | C28: 631901 | D28: 629516 | E28: 628135 | F28: 626989 | G28: 600076
B29: Net Debt | C29: 379844 | D29: 425197 | E29: 425892 | F29: 365250 | G29: 292193
B30: Tangible Assets | C30: 22277 | D30: 19727 | E30: 18761 | F30: 19412 | G30: 17144
B31: Invested Capital | C31: 1732787 | D31: 1761831 | E31: 1768124 | F31: 1357922 | G31: 1318509
B32: NCAV | C32: -839220 | D32: -833591 | E32: -816198 | F32: -758935 | G32: -718466
B33: Shares | C33: 112558 | D33: 107108 | E33: 103193 | F33: 103952 | G33: 112694
B36: D_E | C36: 0.4623 | D36: 0.4666 | E36: 0.4638 | F36: 0.6242 | G36: 0.5786
B37: Assets Growth | C37: 0 | D37: -0.0249 | E37: -0.0066 | F37: -0.1383 | G37: 0.0145
B38: TAGrowth | C38: 0 | D38: -0.1145 | E38: -0.049 | F38: 0.0347 | G38: -0.1168
B39: Equity Growth | C39: 0 | D39: -0.0329 | E39: -0.0122 | F39: -0.2909 | G39: 0.1694
B40: ICGrowth | C40: 0 | D40: 0.0168 | E40: 0.0036 | F40: -0.232 | G40: -0.029
