Workbook

Sheet Main
B3: USD (in thousands) | I3: Price | J3: 10.31
I4: Shares | J4: 185752.51
I5: MC | J5: =J3*J4 -> 1915108.4
I6: Cash | J6: 1280341
I7: Debt | J7: 140634
I8: EV | J8: =J5+J7-J6 -> 775401.35

Sheet Income Statement(a)
C2: 2022 | D2: 2023 | E2: 2024 | F2: 2025 | G2: =F2+1 -> 2026 | H2: =G2+1 -> 2027 | I2: =H2+1 -> 2028 | J2: =I2+1 -> 2029 | K2: =J2+1 -> 2030 | L2: =K2+1 -> 2031 | M2: =L2+1 -> 2032 | N2: =M2+1 -> 2033 | ... P2: =O2+1 -> 2035
B3: Revenue | C3: 70608 | D3: 652902 | E3: 1699837 | F3: =SUM('Income Statement(q)'!E3:H3) -> 1832988 | G3: =F3*1.03 -> 1887977.6 | H3: =G3*1.01 -> 1906857.4 | I3: =H3*1.01 -> 1925926 | J3: =I3*1.01 -> 1945185.3 | K3: =J3*1.01 -> 1964637.1 | L3: =K3*1.01 -> 1984283.5 | M3: =L3*1.01 -> 2004126.3 | N3: =M3*1.01 -> 2024167.6 | O3: =N3*1.01 -> 2044409.2 | P3: =O3*1.01 -> 2064853.3
B4: COGS | C4: -51498 | D4: -375494 | E4: -921344 | F4: =SUM('Income Statement(q)'!E4:H4) -> -972390.07 | G4: =G5-G3 -> -1038387.7 | H4: =H5-H3 -> -1048580.9 | I4: =I5-I3 -> -1058874.1 | J4: =J5-J3 -> -1069268.3 | K4: =K5-K3 -> -1079764.6 | L4: =L5-L3 -> -1090363.8 | M4: =M5-M3 -> -1101067 | N4: =N5-N3 -> -1111875.2 | ... P4: =P5-P3 -> -1133811
B5: Gross Profit | C5: =C3+C4 -> 19110 | D5: =D3+D4 -> 277408 | E5: =E3+E4 -> 778493 | F5: =SUM('Income Statement(q)'!E5:H5) -> 860597.93 | G5: =G3*0.45 -> 849589.94 | H5: =H3*(G5/G3+0.0001) -> 858276.52 | I5: =I3*(H5/H3+0.0001) -> 867051.88 | J5: =J3*(I5/I3+0.0001) -> 875916.92 | K5: =K3*(J5/J3+0.0001) -> 884872.55 | L5: =L3*(K5/K3+0.0001) -> 893919.71 | M5: =M3*(L5/L3+0.0001) -> 903059.31 | N5: =N3*(M5/M3+0.0001) -> 912292.32 | O5: =O3*(N5/N3+0.0001) -> 921619.69 | P5: =P3*(O5/O3+0.0001) -> 931042.37
B6: SG&A | C6: -24865 | D6: -87894 | E6: -304504 | F6: =SUM('Income Statement(q)'!E6:H6) -> -503284.5 | G6: =G3*-0.25 -> -471994.41 | H6: =H3*(G6/G3+0.008) -> -461459.49 | I6: =I3*(H6/H3+0.008) -> -450666.68 | J6: =J3*(I6/I3+0.008) -> -439611.87 | K6: =K3*(J6/J3+0.008) -> -428290.89 | L6: =L3*(K6/K3+0.008) -> -416699.53 | M6: =M3*(L6/L3+0.008) -> -404833.51 | N6: =N3*(M6/M3+0.008) -> -392688.51 | O6: =O3*(N6/N3+0.008) -> -380260.12 | P6: =P3*(O6/O3+0.008) -> -367543.89
B7: R&D | C7: 0 | D7: 0 | E7: 0 | F7: =SUM('Income Statement(q)'!E7:H7) -> 0
B8: Others | C8: -10882 | D8: -38381 | E8: -78462 | F8: =SUM('Income Statement(q)'!E8:H8) -> -95623.3 | G8: =G3*-0.05 -> -94398.882 | H8: =H3*-0.05 -> -95342.871 | I8: =I3*-0.05 -> -96296.3 | J8: =J3*-0.05 -> -97259.263 | K8: =K3*-0.05 -> -98231.855 | L8: =L3*-0.05 -> -99214.174 | M8: =M3*-0.05 -> -100206.32 | N8: =N3*-0.05 -> -101208.38 | ... P8: =P3*-0.05 -> -103242.67
B9: Operating Expense | C9: =C6+C7+C8 -> -35747 | D9: =D6+D7+D8 -> -126275 | E9: =E6+E7+E8 -> -382966 | F9: =SUM('Income Statement(q)'!E9:H9) -> -598907.8 | G9: =G6+G7+G8 -> -566393.29 | H9: =H6+H7+H8 -> -556802.37 | I9: =I6+I7+I8 -> -546962.98 | J9: =J6+J7+J8 -> -536871.13 | K9: =K6+K7+K8 -> -526522.74 | L9: =L6+L7+L8 -> -515913.7 | M9: =M6+M7+M8 -> -505039.83 | N9: =N6+N7+N8 -> -493896.89 | ... P9: =P6+P7+P8 -> -470786.56
B10: Operating Income | C10: =C5+C9 -> -16637 | D10: =D5+D9 -> 151133 | E10: =E5+E9 -> 395527 | F10: =SUM('Income Statement(q)'!E10:H10) -> 261690.13 | G10: =G5+G9 -> 283196.65 | H10: =H5+H9 -> 301474.16 | I10: =I5+I9 -> 320088.9 | J10: =J5+J9 -> 339045.79 | K10: =K5+K9 -> 358349.81 | L10: =L5+L9 -> 378006 | M10: =M5+M9 -> 398019.48 | N10: =N5+N9 -> 418395.44 | ... P10: =P5+P9 -> 460255.81
B11: Net Interest | C11: 275 | D11: 2394 | E11: 5112 | F11: =SUM('Income Statement(q)'!E11:H11) -> 14722
B12: Other Income | C12: 222 | D12: -11931 | E12: 16195 | F12: =SUM('Income Statement(q)'!E12:H12) -> 8069
B13: Pretax Income | C13: =C10+C11+C12 -> -16140 | D13: =D10+D11+D12 -> 141596 | E13: =E10+E11+E12 -> 416834 | F13: =SUM('Income Statement(q)'!E13:H13) -> 284481.13 | G13: =G10+G11+G12 -> 283196.65 | H13: =H10+H11+H12 -> 301474.16 | I13: =I10+I11+I12 -> 320088.9 | J13: =J10+J11+J12 -> 339045.79 | K13: =K10+K11+K12 -> 358349.81 | L13: =L10+L11+L12 -> 378006 | M13: =M10+M11+M12 -> 398019.48 | N13: =N10+N11+N12 -> 418395.44 | ... P13: =P10+P11+P12 -> 460255.81
B14: Taxes | C14: 3111 | D14: -28670 | E14: -72280 | F14: =SUM('Income Statement(q)'!E14:H14) -> -68690.026 | G14: =G13*-0.2 -> -56639.329 | H14: =H13*-0.2 -> -60294.832 | I14: =I13*-0.2 -> -64017.78 | J14: =J13*-0.2 -> -67809.158 | K14: =K13*-0.2 -> -71669.962 | L14: =L13*-0.2 -> -75601.2 | M14: =M13*-0.2 -> -79603.897 | N14: =N13*-0.2 -> -83679.087 | ... P14: =P13*-0.2 -> -92051.162
B15: After-Tax Adj | C15: 0 | D15: -234 | E15: 209 | F15: =SUM('Income Statement(q)'!E15:H15) -> -1373
B16: Net Income | C16: =C13+C14+C15 -> -13029 | D16: =D13+D14+D15 -> 112692 | E16: =E13+E14+E15 -> 344763 | F16: =SUM('Income Statement(q)'!E16:H16) -> 214418.1 | G16: =G13+G14+G15 -> 226557.32 | H16: =H13+H14+H15 -> 241179.33 | I16: =I13+I14+I15 -> 256071.12 | J16: =J13+J14+J15 -> 271236.63 | K16: =K13+K14+K15 -> 286679.85 | L16: =L13+L14+L15 -> 302404.8 | M16: =M13+M14+M15 -> 318415.59 | N16: =N13+N14+N15 -> 334716.35 | ... P16: =P13+P14+P15 -> 368204.65
B17: Other Stockholders | C17: -7841 | D17: -38548 | E17: -148116 | F17: =SUM('Income Statement(q)'!E17:H17) -> -4939
B18: NI Common | C18: =C16+C17 -> -20870 | D18: =D16+D17 -> 74144 | E18: =E16+E17 -> 196647 | F18: =SUM('Income Statement(q)'!E18:H18) -> 209479.1 | G18: =G16+G17 -> 226557.32 | H18: =H16+H17 -> 241179.33 | I18: =I16+I17 -> 256071.12 | J18: =J16+J17 -> 271236.63 | K18: =K16+K17 -> 286679.85 | L18: =L16+L17 -> 302404.8 | M18: =M16+M17 -> 318415.59 | N18: =N16+N17 -> 334716.35 | ... P18: =P16+P17 -> 368204.65 | Q18: =P18*(1+$S$22) -> 371886.69 | R18: =Q18*(1+$S$22) -> 375605.56 | S18: =R18*(1+$S$22) -> 379361.62 | T18: =S18*(1+$S$22) -> 383155.23 | U18: =T18*(1+$S$22) -> 386986.79 | V18: =U18*(1+$S$22) -> 390856.65 | W18: =V18*(1+$S$22) -> 394765.22 | X18: =W18*(1+$S$22) -> 398712.87 | ... GQ18: =GP18*(1+$S$22) -> 2274577.1
B19: Avg Shares | C19: 183550 | D19: 183550 | E19: 183550 | F19: ='Income Statement(q)'!G19 -> 194154
B22: Rev Growth | C22: 0 | D22: =IFERROR((D3-C3)/C3,0) -> 8.2468559 | E22: =IFERROR((E3-D3)/D3,0) -> 1.6035102 | F22: =IFERROR((F3-E3)/E3,0) -> 0.078331628 | G22: =IFERROR((G3-F3)/F3,0) -> 0.03 | H22: =IFERROR((H3-G3)/G3,0) -> 0.01 | I22: =IFERROR((I3-H3)/H3,0) -> 0.01 | J22: =IFERROR((J3-I3)/I3,0) -> 0.01 | K22: =IFERROR((K3-J3)/J3,0) -> 0.01 | ... P22: =IFERROR((P3-O3)/O3,0) -> 0.01 | R22: Maturity | S22: 0.01
B23: Gross Margin | C23: =C5/C3 -> 0.27064922 | D23: =D5/D3 -> 0.42488459 | E23: =E5/E3 -> 0.45798097 | F23: =F5/F3 -> 0.46950549 | G23: =G5/G3 -> 0.45 | H23: =H5/H3 -> 0.4501 | I23: =I5/I3 -> 0.4502 | J23: =J5/J3 -> 0.4503 | ... P23: =P5/P3 -> 0.4509 | R23: Discount | S23: 0.09
B24: Op Margin | C24: =C10/C3 -> -0.23562486 | D24: =D10/D3 -> 0.23147884 | E24: =E10/E3 -> 0.23268525 | F24: =F10/F3 -> 0.14276696 | G24: =G10/G3 -> 0.15 | H24: =H10/H3 -> 0.1581 | I24: =I10/I3 -> 0.1662 | J24: =J10/J3 -> 0.1743 | ... P24: =P10/P3 -> 0.2229 | R24: NPV | S24: =NPV(S23,G18:GQ18)+Main!J6-Main!J7 -> 4930139.1
B25: Net Margin | C25: =C18/C3 -> -0.29557557 | D25: =D18/D3 -> 0.11356069 | E25: =E18/E3 -> 0.1156858 | F25: =F18/F3 -> 0.11428286 | G25: =G18/G3 -> 0.12 | H25: =H18/H3 -> 0.12648 | I25: =I18/I3 -> 0.13296 | J25: =J18/J3 -> 0.13944 | ... P25: =P18/P3 -> 0.17832 | R25: Price | S25: =S24/Main!J4 -> 26.54144
R26: Difference | S26: =S25/Main!J3-1 -> 1.5743395

Sheet Income Statement(q)
C2: FY24Q3 | D2: FY23Q4 | E2: FY25Q1 | F2: FY25Q2 | G2: FY25Q3 | H2: FY25Q4
B3: Revenue | C3: 505149 | D3: 456890 | E3: 467135 | F3: 464561 | G3: 450646 | H3: =G3 -> 450646
B4: COGS | C4: -271701 | D4: -243569 | E4: -240586 | F4: -239946 | G4: -246256 | H4: =H5-H3 -> -245602.07
B5: Gross Profit | C5: =C3+C4 -> 233448 | D5: =D3+D4 -> 213321 | E5: =E3+E4 -> 226549 | F5: =F3+F4 -> 224615 | G5: =G3+G4 -> 204390 | H5: =H3*0.455 -> 205043.93
B6: SG&A | C6: -96371 | D6: -100296 | E6: -89793 | F6: -185389 | G6: -115441 | H6: =H3*-0.25 -> -112661.5
B7: R&D | C7: 0 | D7: 0 | E7: 0 | F7: 0 | G7: 0
B8: Others | C8: -23779 | D8: -24991 | E8: -23745 | F8: -24222 | G8: -25124 | H8: =H3*-0.05 -> -22532.3
B9: Operating Expense | C9: =C6+C7+C8 -> -120150 | D9: =D6+D7+D8 -> -125287 | E9: =E6+E7+E8 -> -113538 | F9: =F6+F7+F8 -> -209611 | G9: =G6+G7+G8 -> -140565 | H9: =H6+H7+H8 -> -135193.8
B10: Operating Income | C10: =C5+C9 -> 113298 | D10: =D5+D9 -> 88034 | E10: =E5+E9 -> 113011 | F10: =F5+F9 -> 15004 | G10: =G5+G9 -> 63825 | H10: =H5+H9 -> 69850.13
B11: Net Interest | C11: 3042 | D11: -166 | E11: 2161 | F11: 7087 | G11: 5474
B12: Other Income | C12: -1039 | D12: 8358 | E12: -56 | F12: 6302 | G12: 1823
B13: Pretax Income | C13: =C10+C11+C12 -> 115301 | D13: =D10+D11+D12 -> 96226 | E13: =E10+E11+E12 -> 115116 | F13: =F10+F11+F12 -> 28393 | G13: =G10+G11+G12 -> 71122 | H13: =H10+H11+H12 -> 69850.13
B14: Taxes | C14: -23060 | D14: -7965 | E14: -21857 | F14: -17624 | G14: -15239 | H14: =H13*-0.2 -> -13970.026
B15: After-Tax Adj | C15: -807 | D15: 2040 | E15: 212 | F15: -1073 | G15: -512
B16: Net Income | C16: =C13+C14+C15 -> 91434 | D16: =D13+D14+D15 -> 90301 | E16: =E13+E14+E15 -> 93471 | F16: =F13+F14+F15 -> 9696 | G16: =G13+G14+G15 -> 55371 | H16: =H13+H14+H15 -> 55880.104
B17: Other Stockholders | C17: -3874 | D17: -136599 | E17: -3993 | F17: -946 | G17: 0
B18: NI Common | C18: =C16+C17 -> 87560 | D18: =D16+D17 -> -46298 | E18: =E16+E17 -> 89478 | F18: =F16+F17 -> 8750 | G18: =G16+G17 -> 55371 | H18: =H16+H17 -> 55880.104
B19: Avg Shares | C19: 183550 | D19: 183550 | E19: 183550 | F19: 185752 | G19: 194154
B22: Rev Growth | C22: 0 | D22: =IFERROR((D3-C3)/C3,0) -> -0.095534189 | E22: =IFERROR((E3-D3)/D3,0) -> 0.02242334 | F22: =IFERROR((F3-E3)/E3,0) -> -0.0055101844 | G22: =IFERROR((G3-F3)/F3,0) -> -0.029953009 | H22: =IFERROR((H3-G3)/G3,0) -> 0
B23: Gross Margin | C23: =C5/C3 -> 0.46213691 | D23: =D5/D3 -> 0.46689794 | E23: =E5/E3 -> 0.48497544 | F23: =F5/F3 -> 0.48349948 | G23: =G5/G3 -> 0.45354891 | H23: =H5/H3 -> 0.455
B24: Op Margin | C24: =C10/C3 -> 0.2242863 | D24: =D10/D3 -> 0.19268095 | E24: =E10/E3 -> 0.24192364 | F24: =F10/F3 -> 0.032297158 | G24: =G10/G3 -> 0.14163002 | H24: =H10/H3 -> 0.155
B25: Net Margin | C25: =C18/C3 -> 0.173335 | D25: =D18/D3 -> -0.10133292 | E25: =E18/E3 -> 0.19154634 | F25: =F18/F3 -> 0.018834986 | G25: =G18/G3 -> 0.12287028 | H25: =H18/H3 -> 0.124

Sheet Cash Flow(a)
C2: 2022 | D2: 2023 | E2: 2024
B3: Net Income | C3: -13028 | D3: 112692 | E3: 344763
B4: D&A | C4: 705 | D4: 1459 | E4: 8345
B5: Change In Working Capital | C5: 20645 | D5: 154247 | E5: 52348
B6: Other Adj | C6: -2142 | D6: 3672 | E6: -16635
B7: CFO | C7: 6180 | D7: 272071 | E7: 388821
B8: Purchase Of Business | C8: 0 | D8: -281 | E8: -1482
B9: Purchase Of Investment | C9: 0 | D9: -47345 | E9: -41107
B10: Sale Of Investment | C10: 65 | D10: 33636 | E10: 41107
B11: Other Investing | C11: -1642 | D11: -6653 | E11: -29962
B12: CFI | C12: -1577 | D12: -20643 | E12: -31444
B13: Repayment Of Debt | C13: 0 | D13: 0 | E13: -3715
B14: Repurchase Of Capital Stock | C14: 0 | D14: 0 | E14: -28786
... B24: Cap Ex | C24: -1542 | D24: -4483 | E24: -33058
B25: FCF | C25: =C23 -> 6180 | D25: =D23 -> 272071 | E25: =E23 -> 388821
B28: CFGrowth | C28: 0 | D28: 43.0223 | E28: 0.4291
B29: CXChange | C29: 0 | D29: 1.9081 | E29: 6.374
B30: FCFGrowth | C30: 0 | D30: 56.6854 | E30: 0.3295
B31: FCFMargin | C31: 0.7506 | D31: 0.9835 | E31: 0.915

Sheet Cash Flow(q)
C2: FY24Q3 | D2: FY23Q4 | E2: FY25Q1 | F2: FY25Q2 | G2: FY25Q3
B3: Net Income | C3: 91434 | D3: 90300 | E3: 93471 | F3: 9696 | G3: 55372
B4: D&A | C4: 0 | D4: 0 | E4: 0 | F4: 0 | G4: 0
B5: Change In Working Capital | C5: 0 | D5: 0 | E5: 0 | F5: 0 | G5: 0
B6: Other Adj | C6: 16193 | D6: -11834 | E6: -43898 | F6: 75513 | G6: 8744
B7: CFO | C7: 107627 | D7: 78466 | E7: 49572 | F7: 85209 | G7: 64115
B8: Purchase Of Business | C8: 0 | D8: 0 | E8: 0 | F8: 0 | G8: 0
B9: Purchase Of Investment | C9: 0 | D9: -41107 | E9: 0 | F9: 0 | G9: 0
B10: Sale Of Investment | C10: 0 | D10: 41107 | E10: 0 | F10: 0 | G10: 0
B11: Other Investing | C11: -11479 | D11: -5847 | E11: -26502 | F11: -16289 | G11: -27459
B12: CFI | C12: -11479 | D12: -5847 | E12: -26502 | F12: -16289 | G12: -27459
B13: Repayment Of Debt | C13: 0 | D13: 0 | E13: 0 | F13: 0 | G13: 0
B14: Repurchase Of Capital Stock | C14: -16416 | D14: 0 | E14: 0 | F14: 0 | G14: 0
... B24: Cap Ex | C24: -14345 | D24: -6180 | E24: 0 | F24: 0 | G24: 0
B25: FCF | C25: =C23 -> 107627 | D25: =D23 -> 78466 | E25: =E23 -> 49572 | F25: =F23 -> 85209 | G25: =G23 -> 64115
B28: CFGrowth | C28: 0 | D28: -0.2709 | E28: -0.3682 | F28: 0.7189 | G28: -0.2476
B29: CXChange | C29: 0 | D29: -0.5692 | E29: 0 | F29: 0 | G29: 0
B30: FCFGrowth | C30: 0 | D30: -0.3284 | E30: -0.3142 | F30: 0.7189 | G30: -0.2476
B31: FCFMargin | C31: 1 | D31: 0.9212 | E31: 1 | F31: 1 | G31: 1

Sheet Balance Sheet(a)
C2: 2022 | D2: 2023 | E2: 2024
B3: Cash & Short Inv | C3: 28830 | D3: 340886 | E3: 665212
B4: Accounts Receivable | C4: 2715 | D4: 13053 | E4: 16712
B5: Inventory | C5: 4766 | D5: 5838 | E5: 18096
B6: Other Current Assets | C6: 3281 | D6: 12845 | E6: 45334
B7: Current Assets | C7: 39592 | D7: 372622 | E7: 745354
B8: PPE | C8: 11146 | D8: 21154 | E8: 110193
B9: Goodwill | C9: 0 | D9: 0 | E9: 1622
B10: Other Assets | C10: 5841 | D10: 20344 | E10: 46643
B11: Non-Current Assets | C11: 16986 | D11: 41498 | E11: 158457
B12: Total Assets | C12: =C7+C11 -> 56578 | D12: =D7+D11 -> 414120 | E12: =E7+E11 -> 903811
B13: Accounts Payable | C13: 9235 | D13: 63081 | E13: 81815
B14: Short Term Debt | C14: 4653 | D14: 7400 | E14: 26779
B15: Other Current Liabilities | C15: 28860 | D15: 134233 | E15: 206273
B16: Current Liabilities | C16: 42747 | D16: 204714 | E16: 314867
B17: Long Term Debt | C17: 4460 | D17: 7914 | E17: 48316
B18: Other Liabilities | C18: 2905 | D18: 19148 | E18: 35256
B19: Non-Current Liabilities | C19: 7365 | D19: 27062 | E19: 83573
B20: Total Liabilities | C20: =C16+C19 -> 50112 | D20: =D16+D19 -> 231776 | E20: =E16+E19 -> 398440
B21: Additional Paid In Capital | C21: 14170 | D21: 11630 | E21: 12449
B22: Retained Earnings | C22: -58331 | D22: 47131 | E22: 377088
B23: Accumulated Other Changes | C23: 50617 | D23: 121426 | E23: 102055
B24: Stockholders Equity | C24: 6456 | D24: 180187 | E24: 491592
B25: Non-Controlling Interest | C25: 10 | D25: 2157 | E25: 13780
B26: Total Equity | C26: =C12+C20 -> 106690 | D26: =D12+D20 -> 645896 | E26: =E12+E20 -> 1302251
B27: Common Stock Equity | C27: -44150 | D27: 57522 | E27: 363643
B28: Total Debt | C28: 9113 | D28: 15314 | E28: 75096
B29: Net Debt | C29: -19717 | D29: -325572 | E29: -590116
B30: Tangible Assets | C30: 15912 | D30: 26993 | E30: 128289
B31: Invested Capital | C31: 6466 | D31: 182344 | E31: 505372
B32: NCAV | C32: -10520 | D32: 140846 | E32: 346915
B33: Shares | C33: 183550 | D33: 183550 | E33: 183550
B36: D_E | C36: 1.4093 | D36: 0.084 | E36: 0.1486
B37: Assets Growth | C37: 0 | D37: 6.3194 | E37: 1.1825
B38: TAGrowth | C38: 0 | D38: 0.6964 | E38: 3.7527
B39: Equity Growth | C39: 0 | D39: 0 | E39: 5.3218
B40: ICGrowth | C40: 0 | D40: 27.1989 | E40: 1.7715

Sheet Balance Sheet(q)
C2: FY24Q3 | D2: FY23Q4 | E2: FY25Q1 | F2: FY25Q2 | G2: FY25Q3
B3: Cash & Short Inv | C3: 617138 | D3: 665212 | E3: 739320 | F3: 1235230 | G3: 1280341
B4: Accounts Receivable | C4: 20485 | D4: 16712 | E4: 18082 | F4: 22342 | G4: 22256
B5: Inventory | C5: 13643 | D5: 18096 | E5: 16170 | F5: 20562 | G5: 24316
B6: Other Current Assets | C6: 42342 | D6: 45334 | E6: 50015 | F6: 49695 | G6: 64474
B7: Current Assets | C7: 693608 | D7: 745354 | E7: 823587 | F7: 1327829 | G7: 1391387
B8: PPE | C8: 98155 | D8: 110193 | E8: 122590 | F8: 151893 | G8: 198649
B9: Goodwill | C9: 1689 | D9: 1622 | E9: 1630 | F9: 1650 | G9: 1663
B10: Other Assets | C10: 27034 | D10: 46643 | E10: 50875 | F10: 61703 | G10: 80029
B11: Non-Current Assets | C11: 126878 | D11: 158457 | E11: 175095 | F11: 215246 | G11: 280340
B12: Total Assets | C12: =C7+C11 -> 820486 | D12: =D7+D11 -> 903811 | E12: =E7+E11 -> 998682 | F12: =F7+F11 -> 1543075 | G12: =G7+G11 -> 1671727
B13: Accounts Payable | C13: 86041 | D13: 81815 | E13: 69946 | F13: 74409 | G13: 76650
B14: Short Term Debt | C14: 22708 | D14: 26779 | E14: 48730 | F14: 33696 | G14: 44383
B15: Other Current Liabilities | C15: 198532 | D15: 206273 | E15: 175776 | F15: 189848 | G15: 208521
B16: Current Liabilities | C16: 307281 | D16: 314867 | E16: 294451 | F16: 297953 | G16: 329554
B17: Long Term Debt | C17: 44200 | D17: 48316 | E17: 59777 | F17: 70798 | G17: 96251
B18: Other Liabilities | C18: 36821 | D18: 35256 | E18: 36752 | F18: 31607 | G18: 29236
B19: Non-Current Liabilities | C19: 81021 | D19: 83573 | E19: 96529 | F19: 102405 | G19: 125487
B20: Total Liabilities | C20: =C16+C19 -> 388302 | D20: =D16+D19 -> 398440 | E20: =E16+E19 -> 390980 | F20: =F16+F19 -> 400358 | G20: =G16+G19 -> 455041
B21: Additional Paid In Capital | C21: 12960 | D21: 12449 | E21: 12509 | F21: 659075 | G21: 679152
B22: Retained Earnings | C22: 306136 | D22: 377088 | E22: 470155 | F22: 485261 | G22: 544225
B23: Accumulated Other Changes | C23: 99511 | D23: 102055 | E23: 104096 | F23: -32073 | G23: -34488
B24: Stockholders Equity | C24: 418607 | D24: 491592 | E24: 586760 | F24: 1112263 | G24: 1188889
B25: Non-Controlling Interest | C25: 13577 | D25: 13780 | E25: 20942 | F25: 30453 | G25: 27797
B26: Total Equity | C26: =C12+C20 -> 1208788 | D26: =D12+D20 -> 1302251 | E26: =E12+E20 -> 1389662 | F26: =F12+F20 -> 1943433 | G26: =G12+G20 -> 2126768
B27: Common Stock Equity | C27: 287720 | D27: 363643 | E27: 586760 | F27: 1112263 | G27: 1188889
B28: Total Debt | C28: 66908 | D28: 75096 | E28: 108506 | F28: 104494 | G28: 140634
B29: Net Debt | C29: -550230 | D29: -590116 | E29: -630814 | F29: -1130735 | G29: -1139707
B30: Tangible Assets | C30: 111798 | D30: 128289 | E30: 138760 | F30: 172455 | G30: 222965
B31: Invested Capital | C31: 432184 | D31: 505372 | E31: 607702 | F31: 1142716 | G31: 1216687
B32: NCAV | C32: 305306 | D32: 346915 | E32: 432607 | F32: 927470 | G32: 936346
B33: Shares | C33: 183550 | D33: 183550 | E33: 183550 | F33: 185752 | G33: 185752
B36: D_E | C36: 0.1548 | D36: 0.1486 | E36: 0.1786 | F36: 0.0914 | G36: 0.1156
B37: Assets Growth | C37: 0 | D37: 0.1016 | E37: 0.105 | F37: 0.5451 | G37: 0.0834
B38: TAGrowth | C38: 0 | D38: 0.1475 | E38: 0.0816 | F38: 0.2428 | G38: 0.2929
B39: Equity Growth | C39: 0 | D39: 0.2639 | E39: 0.6136 | F39: 0.8956 | G39: 0.0689
B40: ICGrowth | C40: 0 | D40: 0.1693 | E40: 0.2025 | F40: 0.8804 | G40: 0.0647
